augflow/__init__.py
augflow/pipeline.py
augflow/augmentations/__init__.py
augflow/augmentations/affine.py
augflow/augmentations/base.py
augflow/augmentations/blur.py
augflow/augmentations/brightness_contrast.py
augflow/augmentations/color_shift.py
augflow/augmentations/crop.py
augflow/augmentations/cutout.py
augflow/augmentations/flip.py
augflow/augmentations/mosaic.py
augflow/augmentations/noise.py
augflow/augmentations/rotate.py
augflow/augmentations/scale.py
augflow/augmentations/shear.py
augflow/augmentations/translate.py
augflow/augmentations/weather.py
augflow/utils/__init__.py
augflow/utils/annotations.py
augflow/utils/configs.py
augflow/utils/images.py
augflow/utils/parsers.py
augflow/utils/unified_format.py
augflow-1.1.0.dist-info/LICENSE
augflow-1.1.0.dist-info/METADATA
augflow-1.1.0.dist-info/WHEEL
augflow-1.1.0.dist-info/top_level.txt
augflow-1.1.0.dist-info/RECORD
