Metadata-Version: 2.1
Name: augflow
Version: 1.1.0
Summary: A versatile augmentation library for computer vision projects.
Home-page: https://github.com/ConnectedMotion/augflow
Author: Omar Alnasier
Author-email: omar@connectedmotion.io
Classifier: Programming Language :: Python :: 3
Classifier: License :: OSI Approved :: MIT License
Classifier: Operating System :: OS Independent
Requires-Python: >=3.6
License-File: LICENSE
Requires-Dist: numpy>=1.18.0
Requires-Dist: opencv-python>=4.1.0
Requires-Dist: shapely>=1.7.0
Requires-Dist: matplotlib>=3.2.0
Requires-Dist: tqdm>=4.50.0
Requires-Dist: PyYAML>=5.3.0
Requires-Dist: pytest
